epylog/__init__.py
epylog/helpers.py
epylog/logger.py
epylog-0.1.33.dist-info/LICENSE
epylog-0.1.33.dist-info/METADATA
epylog-0.1.33.dist-info/WHEEL
epylog-0.1.33.dist-info/top_level.txt
epylog-0.1.33.dist-info/RECORD
