Metadata-Version: 2.1
Name: epylog
Version: 0.1.33
Summary: Just another one Python logging package.
Home-page: https://github.com/iPhosgen/epylog
Author: Alexey Morozov
Author-email: iphosgen@gmail.com
License: MIT License
Keywords: logging
Platform: UNKNOWN
Classifier: License :: OSI Approved :: MIT License
Classifier: Intended Audience :: Developers
Classifier: Programming Language :: Python
Classifier: Programming Language :: Python :: 3.5
Classifier: Programming Language :: Python :: 3.6
Classifier: Programming Language :: Python :: 3.7
Classifier: Programming Language :: Python :: Implementation :: CPython
Classifier: Programming Language :: Python :: Implementation :: PyPy
Classifier: Topic :: System :: Logging
